generalFunctions/__init__.py
generalFunctions/_modidx.py
generalFunctions/core.py
generalFunctions/runModels.py
generalFuncs-0.0.1.dist-info/LICENSE
generalFuncs-0.0.1.dist-info/METADATA
generalFuncs-0.0.1.dist-info/WHEEL
generalFuncs-0.0.1.dist-info/entry_points.txt
generalFuncs-0.0.1.dist-info/top_level.txt
generalFuncs-0.0.1.dist-info/RECORD
